setup_pypi.py
eoclib/__init__.py
eoclib/func.py
eoclib/gui.py
eoclib.egg-info/PKG-INFO
eoclib.egg-info/SOURCES.txt
eoclib.egg-info/dependency_links.txt
eoclib.egg-info/requires.txt
eoclib.egg-info/top_level.txt