Metadata-Version: 1.0
Name: eoclib
Version: 1.33.01.23
Summary: EoC automatic manager platform
Home-page: UNKNOWN
Author: Leniy Tsan
Author-email: m@leniy.org
License: BSD License
Keywords: eoc,amp
Platform: any
